AUTHORS.rst
CONTRIBUTING.rst
HISTORY.rst
LICENSE
MANIFEST.in
README.rst
setup.cfg
setup.py
SimpleTorrentStreaming/SimpleTorrentStreaming.py
SimpleTorrentStreaming/__init__.py
SimpleTorrentStreaming/utils.py
SimpleTorrentStreaming.egg-info/PKG-INFO
SimpleTorrentStreaming.egg-info/SOURCES.txt
SimpleTorrentStreaming.egg-info/dependency_links.txt
SimpleTorrentStreaming.egg-info/entry_points.txt
SimpleTorrentStreaming.egg-info/not-zip-safe
SimpleTorrentStreaming.egg-info/top_level.txt
docs/Makefile
docs/authors.rst
docs/conf.py
docs/contributing.rst
docs/history.rst
docs/index.rst
docs/installation.rst
docs/make.bat
docs/readme.rst
docs/usage.rst
tests/__init__.py
tests/test_SimpleTorrentStreaming.py