Metadata-Version: 1.1
Name: SimpleTorrentStreaming
Version: 0.1.2
Summary: Simple libtorrent-based bittorrent streaming module
Home-page: https://github.com/XayOn/SimpleTorrentStreaming
Author: David Francos
Author-email: me@davidfrancos.net
License: BSD
Keywords: SimpleTorrentStreaming
Platform: UNKNOWN
Classifier: Development Status :: 2 - Pre-Alpha
Classifier: Intended Audience :: Developers
Classifier: License :: OSI Approved :: BSD License
Classifier: Natural Language :: English
Classifier: Programming Language :: Python :: 2
Classifier: Programming Language :: Python :: 2.6
Classifier: Programming Language :: Python :: 2.7
Classifier: Programming Language :: Python :: 3
Classifier: Programming Language :: Python :: 3.3
Classifier: Programming Language :: Python :: 3.4
